jinjafiller/__init__.py
jinjafiller/cla.py
jinjafiller/main.py
jinjafiller-0.0.1a0.dist-info/METADATA
jinjafiller-0.0.1a0.dist-info/WHEEL
jinjafiller-0.0.1a0.dist-info/entry_points.txt
jinjafiller-0.0.1a0.dist-info/top_level.txt
jinjafiller-0.0.1a0.dist-info/RECORD
