Metadata-Version: 2.1
Name: jinjafiller
Version: 0.0.1a0
Summary: Configurable jinja compiler
Home-page: https://github.com/Archiie/jinjafiller
Author: Archita Sundaray
Author-email: archi.sundaray5@gmail.com
License: MIT
Platform: UNKNOWN
Classifier: License :: OSI Approved :: MIT License
Classifier: Programming Language :: Python :: 3
Classifier: Programming Language :: Python :: 3.12
Classifier: Programming Language :: Python :: 3.11
Classifier: Programming Language :: Python :: 3.10
Classifier: Programming Language :: Python :: 3.9
Classifier: Programming Language :: Python :: 3.8
Classifier: Programming Language :: Python :: 3.7
Classifier: Programming Language :: Python :: 3.6
Requires-Dist: Jinja2
